spireg/__init__.py
spireg/__version__.py
spireg/register.py
spireg-0.1.3.dist-info/LICENSE
spireg-0.1.3.dist-info/WHEEL
spireg-0.1.3.dist-info/METADATA
spireg-0.1.3.dist-info/RECORD
