Metadata-Version: 2.3
Name: spireg
Version: 0.1.3
Summary: SPIReg provides a method to define and access SPI registers
Author-email: Daniël van den Berg <daniel@dmvandenberg.nl>
Classifier: License :: OSI Approved :: GNU General Public License v3 or later (GPLv3+)
Classifier: License :: Other/Proprietary License
Requires-Dist: bitstring
Requires-Dist: flake8 ; extra == "dev"
Provides-Extra: dev
